ct_aws_eb_cleaner/__init__.py
ct_aws_eb_cleaner/__main__.py
ct_aws_eb_cleaner/eb_cleaner.py
ct_aws_eb_cleaner-1.0.2.dist-info/METADATA
ct_aws_eb_cleaner-1.0.2.dist-info/WHEEL
ct_aws_eb_cleaner-1.0.2.dist-info/top_level.txt
ct_aws_eb_cleaner-1.0.2.dist-info/RECORD
