Metadata-Version: 2.1
Name: ct-aws-eb-cleaner
Version: 1.0.2
Summary: Python project to clear all applications versions from an ElasticBeanstalk environment that are not implemented.
Home-page: https://bitbucket.org/cinnecta/ct-aws-eb-cleaner/
Author: Cinnecta
Author-email: cinnecta.dev@gmail.com
License: UNKNOWN
Keywords: ct_aws_eb_cleaner
Platform: UNKNOWN
Classifier: Development Status :: 2 - Pre-Alpha
Classifier: Intended Audience :: Developers
Classifier: Natural Language :: English
Classifier: Programming Language :: Python :: 3
Classifier: Programming Language :: Python :: 3.4
Classifier: Programming Language :: Python :: 3.5
Classifier: Programming Language :: Python :: 3.6
Classifier: Programming Language :: Python :: 3.7
